{"name":"年阔正","slug":"blog-author","avatar":"https://foruda.gitee.com/avatar/1689439715159458082/13208566_niankuozheng_1689439715.png","link":"/","description":"一个学知识的学生","socials":{"github":"","twitter":"","stackoverflow":"","wechat":"","qq":"","weibo":"","zhihu":"","csdn":"","juejin":"","customs":{}},"post_list":[{"title":"bom和dom","uid":"0161273db9070c9fd2ff8f89b25e56a1","slug":"bom和dom","date":"2024-10-16T08:50:25.127Z","updated":"2024-10-16T09:41:10.872Z","comments":true,"path":"api/articles/bom和dom.json","keywords":null,"cover":[],"text":"1、JavaScript组成JavaScript由三部分组成： JS的核心语法：注释、标识符、关键字、变量、运算符、判断结构、循环结构、函数、数组、对象 BOM...","permalink":"/post/bom和dom","photos":[],"count_time":{"symbolsCount":"27k","symbolsTime":"24 mins."},"categories":[],"tags":[],"author":{"name":"年阔正","slug":"blog-author","avatar":"https://foruda.gitee.com/avatar/1689439715159458082/13208566_niankuozheng_1689439715.png","link":"/","description":"一个学知识的学生","socials":{"github":"","twitter":"","stackoverflow":"","wechat":"","qq":"","weibo":"","zhihu":"","csdn":"","juejin":"","customs":{}}},"feature":true},{"title":"jQuery-2","uid":"2dc01377f6860c1b2ea08f8dc28dc4ee","slug":"jQuery2","date":"2024-10-16T08:39:46.372Z","updated":"2024-10-16T09:41:00.396Z","comments":true,"path":"api/articles/jQuery2.json","keywords":null,"cover":[],"text":"续接1 1 jQuery（一）jQuery遍历数组的方式数组遍历： 在JS中，我们使用普通for循环即可遍历数组。 在jQuery中，我们可以使数组的遍历变得更...","permalink":"/post/jQuery2","photos":[],"count_time":{"symbolsCount":"13k","symbolsTime":"11 mins."},"categories":[],"tags":[],"author":{"name":"年阔正","slug":"blog-author","avatar":"https://foruda.gitee.com/avatar/1689439715159458082/13208566_niankuozheng_1689439715.png","link":"/","description":"一个学知识的学生","socials":{"github":"","twitter":"","stackoverflow":"","wechat":"","qq":"","weibo":"","zhihu":"","csdn":"","juejin":"","customs":{}}},"feature":true},{"title":"jQuery-1","uid":"6fd616ed0eed6e393880d0a14c94c998","slug":"jQuery1","date":"2024-10-16T08:39:46.363Z","updated":"2024-10-16T09:40:48.666Z","comments":true,"path":"api/articles/jQuery1.json","keywords":null,"cover":[],"text":"Query是一个快速、简洁的JavaScript框架，是继Prototype之后又一个优秀的JavaScript代码库（或JavaScript框架）。jQuer...","permalink":"/post/jQuery1","photos":[],"count_time":{"symbolsCount":"21k","symbolsTime":"19 mins."},"categories":[],"tags":[],"author":{"name":"年阔正","slug":"blog-author","avatar":"https://foruda.gitee.com/avatar/1689439715159458082/13208566_niankuozheng_1689439715.png","link":"/","description":"一个学知识的学生","socials":{"github":"","twitter":"","stackoverflow":"","wechat":"","qq":"","weibo":"","zhihu":"","csdn":"","juejin":"","customs":{}}},"feature":true},{"title":"Javascript","uid":"3ba788290cf8ac86f241d1d02e47bb1a","slug":"Javascript","date":"2024-10-16T08:39:46.354Z","updated":"2024-10-16T09:39:41.979Z","comments":true,"path":"api/articles/Javascript.json","keywords":null,"cover":[],"text":"JavaScript 是一种脚本编程语言，它可以在网页上实现复杂的功能，网页展现给你的不再是简单的静态信息，而是实时的内容更新——交互式的地图、2D/3D 动画...","permalink":"/post/Javascript","photos":[],"count_time":{"symbolsCount":"30k","symbolsTime":"27 mins."},"categories":[],"tags":[],"author":{"name":"年阔正","slug":"blog-author","avatar":"https://foruda.gitee.com/avatar/1689439715159458082/13208566_niankuozheng_1689439715.png","link":"/","description":"一个学知识的学生","socials":{"github":"","twitter":"","stackoverflow":"","wechat":"","qq":"","weibo":"","zhihu":"","csdn":"","juejin":"","customs":{}}}},{"title":"html","uid":"eeae8fb5c624c31359c9eb6c41e321d1","slug":"HTML","date":"2024-10-16T08:39:46.346Z","updated":"2024-10-16T09:40:32.913Z","comments":true,"path":"api/articles/HTML.json","keywords":null,"cover":[],"text":"1、课程介绍主要掌握HTML常用标签，能够灵活使用这些标签编写简单的网页 2、HTML介绍2.1、什么是HTML?我们可以在浏览器里打开任意一个网站页面，它就是...","permalink":"/post/HTML","photos":[],"count_time":{"symbolsCount":"40k","symbolsTime":"36 mins."},"categories":[],"tags":[],"author":{"name":"年阔正","slug":"blog-author","avatar":"https://foruda.gitee.com/avatar/1689439715159458082/13208566_niankuozheng_1689439715.png","link":"/","description":"一个学知识的学生","socials":{"github":"","twitter":"","stackoverflow":"","wechat":"","qq":"","weibo":"","zhihu":"","csdn":"","juejin":"","customs":{}}}},{"title":"css","uid":"4055557ae2c2d8539da38ce5055ff459","slug":"css","date":"2024-10-16T08:39:46.339Z","updated":"2024-10-16T09:40:11.055Z","comments":true,"path":"api/articles/css.json","keywords":null,"cover":[],"text":"1-CSS介绍1.1-web标准W3C组织：他制定web领域中众多的标准。 关于网页的标准：一个网页（界面）应该由4部分组成： 网页内容：网页中需要展示的内容，...","permalink":"/post/css","photos":[],"count_time":{"symbolsCount":"48k","symbolsTime":"44 mins."},"categories":[],"tags":[],"author":{"name":"年阔正","slug":"blog-author","avatar":"https://foruda.gitee.com/avatar/1689439715159458082/13208566_niankuozheng_1689439715.png","link":"/","description":"一个学知识的学生","socials":{"github":"","twitter":"","stackoverflow":"","wechat":"","qq":"","weibo":"","zhihu":"","csdn":"","juejin":"","customs":{}}}},{"title":"MySQL基础","uid":"4a207b7e885fdbcca8129599135e5f2e","slug":"第一篇","date":"2024-10-16T01:28:20.128Z","updated":"2024-10-16T03:43:33.267Z","comments":true,"path":"api/articles/第一篇.json","keywords":null,"cover":[],"text":" MySQL基础数据库概论数据管理演变 人工档案管理 文件系统管理 数据库管理 数据库管理系统 层次数据库 网状型数据库 关系型数据库 网格型数据库 对象型数据...","permalink":"/post/第一篇","photos":[],"count_time":{"symbolsCount":"76k","symbolsTime":"1:09"},"categories":[],"tags":[],"author":{"name":"年阔正","slug":"blog-author","avatar":"https://foruda.gitee.com/avatar/1689439715159458082/13208566_niankuozheng_1689439715.png","link":"/","description":"一个学知识的学生","socials":{"github":"","twitter":"","stackoverflow":"","wechat":"","qq":"","weibo":"","zhihu":"","csdn":"","juejin":"","customs":{}}}},{"title":"Hello World","uid":"b9663f58f18133b35bfe243f3e916a80","slug":"hello-world","date":"2024-10-16T01:24:11.687Z","updated":"2024-10-16T06:25:17.709Z","comments":true,"path":"api/articles/hello-world.json","keywords":null,"cover":[],"text":"Welcome to Hexo! This is your very first post. Check documentation for more info...","permalink":"/post/hello-world","photos":[],"count_time":{"symbolsCount":445,"symbolsTime":"1 mins."},"categories":[],"tags":[],"author":{"name":"年阔正","slug":"blog-author","avatar":"https://foruda.gitee.com/avatar/1689439715159458082/13208566_niankuozheng_1689439715.png","link":"/","description":"一个学知识的学生","socials":{"github":"","twitter":"","stackoverflow":"","wechat":"","qq":"","weibo":"","zhihu":"","csdn":"","juejin":"","customs":{}}}}],"categories":0,"tags":0,"word_count":"255k","post_count":8}